CoSQL/__init__.py
CoSQL/__version__.py
CoSQL/context.py
CoSQL/core.py
CoSQL/cursor.py
CoSQL-1.3.0.dist-info/METADATA
CoSQL-1.3.0.dist-info/WHEEL
CoSQL-1.3.0.dist-info/top_level.txt
CoSQL-1.3.0.dist-info/RECORD
